LICENSE
README.md
setup.cfg
setup.py
pyndv/__init__.py
pyndv/__main__.py
pyndv.egg-info/PKG-INFO
pyndv.egg-info/SOURCES.txt
pyndv.egg-info/dependency_links.txt
pyndv.egg-info/entry_points.txt
pyndv.egg-info/requires.txt
pyndv.egg-info/top_level.txt
pyndv/core/__init__.py
tests/__init__.py
tests/conftest.py
tests/test_core.py
tests/test_subprocess.py